projectXapi/__init__.py
projectXapi/flask/__init__.py
projectXapi/flask/app.py
projectXapi/flask/exception.py
projectXapi/flask/utils.py
projectXapi/util/__init__.py
projectXapi/util/datetime_utils.py
projectXapi/util/logger.py
ProjectXapi_projectX_IbTws-0.0.7.dist-info/LICENSE
ProjectXapi_projectX_IbTws-0.0.7.dist-info/METADATA
ProjectXapi_projectX_IbTws-0.0.7.dist-info/WHEEL
ProjectXapi_projectX_IbTws-0.0.7.dist-info/top_level.txt
ProjectXapi_projectX_IbTws-0.0.7.dist-info/RECORD
